griffe_generics/__init__.py
griffe_generics/extension.py
griffe_generics/inspector.py
griffe_generics/models.py
griffe_generics/predicates.py
griffe_generics/py.typed
griffe_generics/transforms.py
griffe_generics/traversal.py
griffe_generics/types.py
griffe_generics/utils.py
tests/__init__.py
tests/conftest.py
tests/test_extension.py
tests/utils.py
griffe_generics-1.0.13.dist-info/LICENSE
griffe_generics-1.0.13.dist-info/METADATA
griffe_generics-1.0.13.dist-info/WHEEL
griffe_generics-1.0.13.dist-info/top_level.txt
griffe_generics-1.0.13.dist-info/RECORD
